vcfio/__init__.py
vcfio/utils/__init__.py
vcfio/utils/consts.py
vcfio/utils/easy_dict.py
vcfio/utils/enums.py
vcfio/utils/exceptions.py
vcfio/utils/file_utils.py
vcfio/utils/regex_patterns.py
vcfio/utils/str_utils.py
vcfio/variant/__init__.py
vcfio/variant/variant.py
vcfio/variant/variant_properties.py
vcfio/vcf_reader.py
vcfio/vcf_writer.py
vcfio-1.2.0.dist-info/LICENSE
vcfio-1.2.0.dist-info/METADATA
vcfio-1.2.0.dist-info/WHEEL
vcfio-1.2.0.dist-info/RECORD
