Metadata-Version: 2.3
Name: vcfio
Version: 1.2.0
Summary: A simple and efficient VCF manipulation package.
License: MIT
Keywords: vcf,variant,genetics,bioinformatics,emedgene,illumina
Author: shencar
Author-email: barak.shencar@gmail.com
Maintainer: shencar
Maintainer-email: barak.shencar@gmail.com
Requires-Python: >=3.6,<4.0
Classifier: License :: OSI Approved :: MIT License
Classifier: Programming Language :: Python :: 3
Classifier: Programming Language :: Python :: 3.6
Classifier: Programming Language :: Python :: 3.7
Classifier: Programming Language :: Python :: 3.8
Classifier: Programming Language :: Python :: 3.9
Classifier: Programming Language :: Python :: 3.10
Classifier: Programming Language :: Python :: 3.11
Classifier: Programming Language :: Python :: 3.12
Classifier: Programming Language :: Python :: 3.13
Provides-Extra: bio
Requires-Dist: biopython (>=1.79,<2.0) ; extra == "bio"
Requires-Dist: pysam (>=0.18,<0.19) ; extra == "bio"
Project-URL: Repository, https://github.com/emedgene/vcfio
